blog/blog.py
blog/build_blog.py
examples/async_infrastructure_example.py
examples/auto_remediation_demo.py
examples/dns_example.py
examples/dns_record_example.py
examples/lego_principle_demo.py
examples/monitoring_notifications_demo.py
examples/multi_channel_notifications.py
examples/simple_monitoring_demo.py
examples/simple_vm_with_notifications.py
examples/simple_vm_with_notifications_fixed.py
examples/vm_examples.py
helloworld/app.py
infradsl/__init__.py
infradsl/notifications.py
infradsl/py.typed
infradsl/regions.py
infradsl/auth/__init__.py
infradsl/auth/firebase_auth.py
infradsl/cli/__init__.py
infradsl/cli/__main__.py
infradsl/cli/main.py
infradsl/cli/registry.py
infradsl/cli/commands/__init__.py
infradsl/cli/commands/async_apply.py
infradsl/cli/commands/auth.py
infradsl/cli/commands/base.py
infradsl/cli/commands/cache.py
infradsl/cli/commands/config.py
infradsl/cli/commands/create_template.py
infradsl/cli/commands/destroy.py
infradsl/cli/commands/discover.py
infradsl/cli/commands/drift.py
infradsl/cli/commands/generate.py
infradsl/cli/commands/heal.py
infradsl/cli/commands/health.py
infradsl/cli/commands/import.py
infradsl/cli/commands/import_cmd.py
infradsl/cli/commands/init.py
infradsl/cli/commands/insights.py
infradsl/cli/commands/monitor.py
infradsl/cli/commands/preview.py
infradsl/cli/commands/provider.py
infradsl/cli/commands/registry.py
infradsl/cli/commands/remediate.py
infradsl/cli/commands/serve.py
infradsl/cli/commands/state.py
infradsl/cli/commands/visualize.py
infradsl/cli/commands/apply/__init__.py
infradsl/cli/commands/apply/cache_manager.py
infradsl/cli/commands/apply/command.py
infradsl/cli/commands/apply/display.py
infradsl/cli/commands/apply/executor.py
infradsl/cli/commands/apply/lego_analyzer.py
infradsl/cli/commands/apply/loader.py
infradsl/cli/commands/apply/planner.py
infradsl/cli/commands/apply/state_analyzer.py
infradsl/cli/commands/preview_modules/__init__.py
infradsl/cli/commands/preview_modules/cache_lookup.py
infradsl-0.1.5.dist-info/METADATA
infradsl-0.1.5.dist-info/WHEEL
infradsl-0.1.5.dist-info/entry_points.txt
infradsl-0.1.5.dist-info/top_level.txt
infradsl-0.1.5.dist-info/RECORD
