Metadata-Version: 2.4
Name: infradsl
Version: 0.1.5
Summary: The Rails of Modern Infrastructure - Enterprise DSL for Infrastructure Management
Author-email: InfraDSL Team <team@infradsl.dev>
License-Expression: MIT
Project-URL: Homepage, https://infradsl.dev
Project-URL: Documentation, https://docs.infradsl.dev
Project-URL: Repository, https://github.com/infradsl/infradsl
Project-URL: Issues, https://github.com/infradsl/infradsl/issues
Classifier: Development Status :: 3 - Alpha
Classifier: Intended Audience :: Developers
Classifier: Intended Audience :: System Administrators
Classifier: Programming Language :: Python :: 3
Classifier: Programming Language :: Python :: 3.9
Classifier: Programming Language :: Python :: 3.10
Classifier: Programming Language :: Python :: 3.11
Classifier: Programming Language :: Python :: 3.12
Classifier: Topic :: Software Development :: Libraries :: Python Modules
Classifier: Topic :: System :: Systems Administration
Classifier: Topic :: Internet :: WWW/HTTP :: HTTP Servers
Requires-Python: >=3.9
Requires-Dist: pydantic>=2.0.0
Requires-Dist: click>=8.0.0
Requires-Dist: rich>=13.0.0
Requires-Dist: boto3>=1.26.0
Requires-Dist: google-cloud-compute>=1.0.0
Requires-Dist: google-cloud-storage>=2.0.0
Requires-Dist: azure-mgmt-compute>=30.0.0
Requires-Dist: azure-identity>=1.12.0
Requires-Dist: python-digitalocean>=1.17.0
Requires-Dist: cloudflare>=2.19.0
Requires-Dist: pyyaml>=6.0
Requires-Dist: jinja2>=3.1.0
Requires-Dist: requests>=2.28.0
Requires-Dist: aiohttp>=3.8.0
Requires-Dist: asyncio-mqtt>=0.11.0
Requires-Dist: schedule>=1.2.0
Requires-Dist: python-dotenv>=1.0.0
Requires-Dist: pytest-asyncio>=0.21.0
Requires-Dist: pytest-cov>=4.0.0
Requires-Dist: fastapi>=0.100.0
Requires-Dist: mkdocs>=1.5.0
Requires-Dist: mkdocs-material>=9.4.0
Requires-Dist: mkdocstrings[python]>=0.24.0
Requires-Dist: uvicorn[standard]>=0.23.0
Requires-Dist: websockets>=11.0
Requires-Dist: grpcio>=1.73.1
Requires-Dist: grpcio-tools>=1.60.0
Requires-Dist: tabulate>=0.9.0
Requires-Dist: networkx>=3.0
Requires-Dist: asyncpg>=0.29.0
Requires-Dist: redis>=5.0.0
Requires-Dist: watchdog>=3.0.0
Provides-Extra: dev
Requires-Dist: pytest>=7.0.0; extra == "dev"
Requires-Dist: pytest-asyncio>=0.21.0; extra == "dev"
Requires-Dist: pytest-cov>=4.0.0; extra == "dev"
Requires-Dist: black>=23.0.0; extra == "dev"
Requires-Dist: isort>=5.12.0; extra == "dev"
Requires-Dist: flake8>=6.0.0; extra == "dev"
Requires-Dist: mypy>=1.0.0; extra == "dev"
Requires-Dist: pre-commit>=3.0.0; extra == "dev"
Provides-Extra: aws
Requires-Dist: boto3>=1.26.0; extra == "aws"
Requires-Dist: botocore>=1.29.0; extra == "aws"
Provides-Extra: gcp
Requires-Dist: google-cloud-compute>=1.0.0; extra == "gcp"
Requires-Dist: google-cloud-storage>=2.0.0; extra == "gcp"
Requires-Dist: google-cloud-dns>=0.35.0; extra == "gcp"
Requires-Dist: google-auth>=2.17.0; extra == "gcp"
Provides-Extra: azure
Requires-Dist: azure-mgmt-compute>=30.0.0; extra == "azure"
Requires-Dist: azure-identity>=1.12.0; extra == "azure"
Requires-Dist: azure-mgmt-resource>=23.0.0; extra == "azure"
Provides-Extra: digitalocean
Requires-Dist: python-digitalocean>=1.17.0; extra == "digitalocean"
Provides-Extra: cloudflare
Requires-Dist: cloudflare>=2.19.0; extra == "cloudflare"
Provides-Extra: performance
Requires-Dist: asyncpg>=0.29.0; extra == "performance"
Requires-Dist: redis>=5.0.0; extra == "performance"
Requires-Dist: psycopg2>=2.9.0; extra == "performance"
Requires-Dist: hiredis>=2.2.0; extra == "performance"
